GOSTnets/__init__.py
GOSTnets/calculate_od_raw.py
GOSTnets/conversion_utils.py
GOSTnets/core.py
GOSTnets/fetch_od.py
GOSTnets/fetch_pois.py
GOSTnets/load_osm.py
GOSTnets/network_clean.py
GOSTnets/optimization.py
GOSTnets/osm_parser.py
GOSTnets/utils/graphtool.py
gostnets-1.2.0.dist-info/LICENSE
gostnets-1.2.0.dist-info/METADATA
gostnets-1.2.0.dist-info/WHEEL
gostnets-1.2.0.dist-info/top_level.txt
gostnets-1.2.0.dist-info/RECORD
