Metadata-Version: 2.1
Name: GOSTnets
Version: 1.2.0
Summary: Network wrapper to simplify network analysis using geospatial data
Author-email: World Bank <github@worldbank.org>
Maintainer-email: "Benjamin P. Stewart" <bstewart@worldbankgroup.org>, Andres Chamorro <achamorroelizond@worldbank.org>
Project-URL: Homepage, https://github.com/worldbank/GOSTnets
Project-URL: Bug Reports, https://github.com/worldbank/GOSTnets/issues
Project-URL: Source, https://github.com/worldbank/GOSTnets
Classifier: Programming Language :: Python :: 3 :: Only
Classifier: Development Status :: 3 - Alpha
Classifier: Intended Audience :: Developers
Classifier: Operating System :: OS Independent
Requires-Python: >=3.8
License-File: LICENSE
Requires-Dist: geojson
Requires-Dist: geopandas
Requires-Dist: networkx
Requires-Dist: numpy
Requires-Dist: osmnx <2,>=1.0.1
Requires-Dist: pandas >=0.23.5
Requires-Dist: pyproj >=2.4.2
Requires-Dist: rasterio
Requires-Dist: rtree >=0.9.3
Requires-Dist: scipy
Requires-Dist: shapely
Requires-Dist: boltons
Requires-Dist: geopy
Provides-Extra: dev
Requires-Dist: pre-commit ; extra == 'dev'
Requires-Dist: pytest ; extra == 'dev'
Requires-Dist: pytest-cov ; extra == 'dev'
Requires-Dist: tomli ; extra == 'dev'
Requires-Dist: coverage[toml] ; extra == 'dev'
Requires-Dist: docutils ==0.17.1 ; extra == 'dev'
Requires-Dist: jupyter-book <3,>=2 ; extra == 'dev'
Requires-Dist: sphinxcontrib-apidoc <1,>=0.4.0 ; extra == 'dev'
Requires-Dist: jupyter-cache >=0.6.0 ; extra == 'dev'
Requires-Dist: nbconvert ; extra == 'dev'
Requires-Dist: pooch ; extra == 'dev'
Requires-Dist: pulp ; extra == 'dev'
